{
  "Date" : "Data",
  "Date Format" : "Format de la data",
  "Default Location" : "Ubicació per defecte",
  "Default db location hint" : "Per defecte es desarà a {{location}}",
  "Delete" : "Suprimeix",
  "Italic" : "Cursiva",
  "Heading" : "Encapçalament {{number}}",
  "Export Description" : "Podeu exportar l'espai de treball sencer per fer-ne una còpia de seguretat i reimportar les dades.",
  "Got it" : "Entesos",
  "Export" : "Exporta",
  "404 - Page Not Found" : "404 - No s'ha trobat la pàgina",
  "Access level" : "Nivell d'accés",
  "Add Filter" : "Afegeix filtre",
  "Add Workspace" : "Afegeix espai de treball",
  "Add a subpage inside" : "Afegeix una subpàgina dins",
  "Add to Favorites" : "Afegeix a preferits",
  "Add to favorites" : "Afegeix a preferits",
  "Added Successfully" : "S'ha afegit amb èxit",
  "Added to Favorites" : "S'ha afegit a preferits",
  "All pages" : "Totes les pàgines",
  "App Version" : "Versió de l'aplicació",
  "Bold" : "Negreta",
  "Cancel" : "Cancel·la",
  "Collections" : "Col·leccions",
  "Copy" : "Copia",
  "Copy Link" : "Copia enllaç",
  "Copied link to clipboard" : "S'ha copiat l'enllaç al porta-retalls",
  "Quick Search" : "Cerca ràpida",
  "Export AFFiNE backup file" : "Exporta l'arxiu de còpia de seguretat",
  "Convert to " : "Converteix a",
  "Moved to Trash" : "S'ha mogut a la paperera",
  "Move to Trash" : "Mou a la paperera",
  "Trash" : "Paperera de reciclatge",
  "Settings" : "Configuració",
  "Workspace Settings" : "Configuració de l'espai de treball",
  "com" : {
    "affine" : {
      "settings" : {
        "appearance" : {
          "start-week-description" : "Per defecte, la setmana comença el diumenge."
        },
        "suggestion" : "Us calen més opcions de personalització? Expliqueu-nos-ho a la comunitat."
      },
      "cloudTempDisable" : {
        "description" : "Estem actualitzant el servei de Núvol d'AFFiNE i temporalment no és disponible per als usuaris. Si voleu estar al dia del progrés i ser notificat quan sigui disponible, podeu omplir el <1>Registre del Núvol d'AFFiNE</1>."
      },
      "export" : {
        "success" : {
          "title" : "S'ha exportat exitosament"
        }
      },
      "workspaceSubPath" : {
        "all" : "Totes les pàgines"
      },
      "collection-bar" : {
        "action" : {
          "tooltip" : {
            "delete" : "Suprimeix",
            "edit" : "Edita"
          }
        }
      },
      "workspaceType" : {
        "offline" : "Disponible sense connexió"
      },
      "aboutAFFiNE" : {
        "legal" : {
          "title" : "Informació legal",
          "tos" : "Condicions d’ús"
        },
        "version" : {
          "app" : "Versió de l'aplicació",
          "editor" : {
            "title" : "Versió de l'editor"
          },
          "title" : "Versió"
        },
        "subtitle" : "Informació sobre AFFiNE"
      },
      "appUpdater" : {
        "downloading" : "S'està descarregant",
        "updateAvailable" : "Actualització disponible"
      },
      "appearanceSettings" : {
        "font" : {
          "description" : "Trieu l'estil de la lletra",
          "title" : "Estil de la lletra"
        }
      },
      "keyboardShortcuts" : {
        "cancel" : "Cancel·la",
        "quickSearch" : "Cerca ràpida",
        "newPage" : "Nova pàgina",
        "redo" : "Refés",
        "undo" : "Desfés",
        "italic" : "Cursiva",
        "bold" : "Negreta",
        "heading" : "Encapçalament {{number}}",
        "image" : "Imatge",
        "note" : "Nota"
      },
      "write_with_a_blank_page" : "Escriviu a una pàgina en blanc",
      "cmdk" : {
        "affine" : {
          "category" : {
            "affine" : {
              "collections" : "Col·leccions"
            }
          }
        }
      },
      "editCollection" : {
        "button" : {
          "create" : "Crea"
        },
        "save" : "Desa",
        "untitledCollection" : "Col·lecció sense títol"
      },
      "rootAppSidebar" : {
        "collections" : "Col·leccions"
      }
    }
  },
  "New Page" : "Nova pàgina",
  "Export to HTML" : "Exporta a HTML",
  "Export to Markdown" : "Exporta a Markdown",
  "Export to PDF" : "Exporta a PDF",
  "Export to PNG" : "Exporta a PNG",
  "Delete Member?" : "Suprimeix el membre?",
  "Delete Workspace" : "Suprimeix l'espai de treball",
  "Delete Workspace placeholder" : null,
  "Confirm" : "Confirma",
  "Tags" : "Etiquetes",
  "Import" : "Importa",
  "Create Or Import" : "Crea o importa",
  "About AFFiNE" : "Quant a AFFiNE",
  "Appearance Settings" : "Configuració d'aparença",
  "Font Style" : "Estil de la lletra",
  "Choose your font style" : "Trieu l'estil de la lletra",
  "Keyboard Shortcuts" : "Dreceres de teclat",
  "Pen" : "Bolígraf",
  "Create a collection" : "Crea una col·lecció",
  "Untitled Collection" : "Col·lecció sense títol",
  "Available Offline" : "Disponible sense connexió",
  "Create" : "Crea",
  "All data has been stored in the cloud" : "S'han desat totes les dades al núvol."
}